pygenten/helpers.py
pygenten/nlohmann_json.natvis
pygenten/solvers.py
pygenten/utils.py
pygenten/_pygenten.cp38-win_amd64.pyd
pygenten/__init__.py
pygenten/bin/convert_tensor.exe
pygenten/bin/genten.exe
pygenten/bin/hpcbind
pygenten/bin/kokkos_launch_compiler
pygenten/bin/nvcc_wrapper
pygenten/bin/read_binary_header.exe
pygenten/cmake/GentenConfig.cmake
pygenten/cmake/GentenConfigVersion.cmake
pygenten/cmake/genten_setup_deps.cmake
pygenten/cmake/genten_setup_targets.cmake
pygenten/include/genten/CMakeInclude.h
pygenten/include/genten/Genten_AlgParams.hpp
pygenten/include/genten/Genten_Annealer.hpp
pygenten/include/genten/Genten_Array.hpp
pygenten/include/genten/Genten_assert.hpp
pygenten/include/genten/Genten_CpAls.hpp
pygenten/include/genten/Genten_CP_Model.hpp
pygenten/include/genten/Genten_CP_Opt_Lbfgsb.hpp
pygenten/include/genten/Genten_CP_Opt_Rol.hpp
pygenten/include/genten/Genten_CP_RolObjective.hpp
pygenten/include/genten/Genten_CublasHandle.hpp
pygenten/include/genten/Genten_CusolverHandle.hpp
pygenten/include/genten/Genten_DiscreteCDF.hpp
pygenten/include/genten/Genten_DistContext.hpp
pygenten/include/genten/Genten_DistFacMatrix.hpp
pygenten/include/genten/Genten_DistKtensorUpdate.hpp
pygenten/include/genten/Genten_DistTensor.hpp
pygenten/include/genten/Genten_DistTensorContext.hpp
pygenten/include/genten/Genten_Driver.hpp
pygenten/include/genten/Genten_FacMatArray.hpp
pygenten/include/genten/Genten_FacMatrix.hpp
pygenten/include/genten/Genten_FacTestSetGenerator.hpp
pygenten/include/genten/Genten_GCP_BernoulliLossFunction.hpp
pygenten/include/genten/Genten_GCP_DenseSampler.hpp
pygenten/include/genten/Genten_GCP_FedOpt.hpp
pygenten/include/genten/Genten_GCP_GammaLossFunction.hpp
pygenten/include/genten/Genten_GCP_GaussianLossFunction.hpp
pygenten/include/genten/Genten_GCP_Goal.hpp
pygenten/include/genten/Genten_GCP_GradientKernels.hpp
pygenten/include/genten/Genten_GCP_Hash.hpp
pygenten/include/genten/Genten_GCP_LossFunctions.hpp
pygenten-0.1.5.dist-info/DELVEWHEEL
pygenten-0.1.5.dist-info/METADATA
pygenten-0.1.5.dist-info/RECORD
pygenten-0.1.5.dist-info/WHEEL
pygenten-0.1.5.dist-info/licenses/LICENSE.txt
