Metadata-Version: 2.2
Name: pygenten
Version: 0.1.5
Summary: A Python interace to the GenTen tensor decomposition library
Author: Eric Phipps
Classifier: Development Status :: 4 - Beta
Classifier: License :: OSI Approved :: BSD License
Classifier: Programming Language :: Python :: 3 :: Only
Requires-Python: >=3.8
Requires-Dist: numpy
